{
	"info": {
		"_postman_id": "55432586-6d1d-4cdf-9dd2-d29a405a9515",
		"name": "Capstone",
		"description": "This is for the capstone project",
		"schema": "https://schema.getpostman.com/json/collection/v2.1.0/collection.json"
	},
	"item": [
		{
			"name": "public",
			"item": [
				{
					"name": "/actors",
					"request": {
						"method": "POST",
						"header": [],
						"body": {
							"mode": "raw",
							"raw": "{\n    \"name\": \"Leonardo DiCaprio\",\n    \"age\": \"45\",\n    \"gender\": \"Male\"\n}\n",
							"options": {
								"raw": {
									"language": "json"
								}
							}
						},
						"url": {
							"raw": "{{host}}/actors",
							"host": [
								"{{host}}"
							],
							"path": [
								"actors"
							]
						}
					},
					"response": []
				},
				{
					"name": "/movies",
					"request": {
						"method": "POST",
						"header": [],
						"body": {
							"mode": "raw",
							"raw": "{\n    \"title\": \"The Other Guys\",\n    \"release_date\": \"08-06-2010\"\n}\n",
							"options": {
								"raw": {
									"language": "json"
								}
							}
						},
						"url": {
							"raw": "{{host}}/movies",
							"host": [
								"{{host}}"
							],
							"path": [
								"movies"
							]
						}
					},
					"response": []
				},
				{
					"name": "/movies",
					"request": {
						"method": "GET",
						"header": [],
						"url": {
							"raw": "{{host}}/movies",
							"host": [
								"{{host}}"
							],
							"path": [
								"movies"
							]
						}
					},
					"response": []
				},
				{
					"name": "/actors",
					"request": {
						"method": "GET",
						"header": [],
						"url": {
							"raw": "{{host}}/actors",
							"host": [
								"{{host}}"
							],
							"path": [
								"actors"
							]
						}
					},
					"response": []
				},
				{
					"name": "/movies",
					"request": {
						"method": "PATCH",
						"header": [],
						"body": {
							"mode": "raw",
							"raw": "{\n    \"release_date\": \"08-06-2012\"\n}\n",
							"options": {
								"raw": {
									"language": "json"
								}
							}
						},
						"url": {
							"raw": "{{host}}/movies/2",
							"host": [
								"{{host}}"
							],
							"path": [
								"movies",
								"2"
							]
						}
					},
					"response": []
				},
				{
					"name": "/actors",
					"request": {
						"method": "PATCH",
						"header": [],
						"body": {
							"mode": "raw",
							"raw": "{\n    \"gender\": \"Female\"\n}\n",
							"options": {
								"raw": {
									"language": "json"
								}
							}
						},
						"url": {
							"raw": "{{host}}/actors/2",
							"host": [
								"{{host}}"
							],
							"path": [
								"actors",
								"2"
							]
						}
					},
					"response": []
				},
				{
					"name": "/movies",
					"request": {
						"method": "DELETE",
						"header": [],
						"url": {
							"raw": "{{host}}/movies/2",
							"host": [
								"{{host}}"
							],
							"path": [
								"movies",
								"2"
							]
						}
					},
					"response": []
				},
				{
					"name": "/actors",
					"request": {
						"method": "DELETE",
						"header": [],
						"url": {
							"raw": "{{host}}/actors/2",
							"host": [
								"{{host}}"
							],
							"path": [
								"actors",
								"2"
							]
						}
					},
					"response": []
				}
			],
			"description": "Public",
			"protocolProfileBehavior": {}
		},
		{
			"name": "Casting Director",
			"item": [
				{
					"name": "/actors",
					"request": {
						"method": "POST",
						"header": [],
						"body": {
							"mode": "raw",
							"raw": "{\n    \"name\": \"Leonardo DiCaprio\",\n    \"age\": \"45\",\n    \"gender\": \"Male\"\n}\n",
							"options": {
								"raw": {
									"language": "json"
								}
							}
						},
						"url": {
							"raw": "{{host}}/actors",
							"host": [
								"{{host}}"
							],
							"path": [
								"actors"
							]
						}
					},
					"response": []
				},
				{
					"name": "/movies",
					"request": {
						"method": "POST",
						"header": [],
						"body": {
							"mode": "raw",
							"raw": "{\n    \"title\": \"The Other Guys\",\n    \"release_date\": \"08-06-2010\"\n}\n",
							"options": {
								"raw": {
									"language": "json"
								}
							}
						},
						"url": {
							"raw": "{{host}}/movies",
							"host": [
								"{{host}}"
							],
							"path": [
								"movies"
							]
						}
					},
					"response": []
				},
				{
					"name": "/actors",
					"request": {
						"method": "GET",
						"header": [],
						"url": {
							"raw": "{{host}}/actors",
							"host": [
								"{{host}}"
							],
							"path": [
								"actors"
							]
						}
					},
					"response": []
				},
				{
					"name": "/movies",
					"request": {
						"method": "GET",
						"header": [],
						"url": {
							"raw": "{{host}}/movies",
							"host": [
								"{{host}}"
							],
							"path": [
								"movies"
							]
						}
					},
					"response": []
				},
				{
					"name": "/movies",
					"request": {
						"method": "PATCH",
						"header": [],
						"body": {
							"mode": "raw",
							"raw": "{\n    \"release_date\": \"08-06-2012\"\n}\n",
							"options": {
								"raw": {
									"language": "json"
								}
							}
						},
						"url": {
							"raw": "{{host}}/movies/1",
							"host": [
								"{{host}}"
							],
							"path": [
								"movies",
								"1"
							]
						}
					},
					"response": []
				},
				{
					"name": "/actors",
					"request": {
						"method": "PATCH",
						"header": [],
						"body": {
							"mode": "raw",
							"raw": "{\n    \"gender\": \"Female\"\n}\n",
							"options": {
								"raw": {
									"language": "json"
								}
							}
						},
						"url": {
							"raw": "{{host}}/actors/1",
							"host": [
								"{{host}}"
							],
							"path": [
								"actors",
								"1"
							]
						}
					},
					"response": []
				},
				{
					"name": "/actors",
					"request": {
						"method": "DELETE",
						"header": [],
						"url": {
							"raw": "{{host}}/actors/2",
							"host": [
								"{{host}}"
							],
							"path": [
								"actors",
								"2"
							]
						}
					},
					"response": []
				},
				{
					"name": "/movies",
					"request": {
						"method": "DELETE",
						"header": [],
						"url": {
							"raw": "{{host}}/movies/4",
							"host": [
								"{{host}}"
							],
							"path": [
								"movies",
								"4"
							]
						}
					},
					"response": []
				}
			],
			"auth": {
				"type": "bearer",
				"bearer": [
					{
						"key": "token",
						"value": "eyJhbGciOiJSUzI1NiIsInR5cCI6IkpXVCIsImtpZCI6Ik5FRTBRakpEUXpjM05qSTRNVEV5UlRRelEwVTRNa0ZDUmpKRVFUQTFSVVkwTnpJek1VSkdRdyJ9.eyJpc3MiOiJodHRwczovL2pvbnNoZWZmZXIuYXV0aDAuY29tLyIsInN1YiI6ImF1dGgwfDVlNWVkNGZmY2U5YzgyMGQ1ZTFjNzkzZCIsImF1ZCI6ImNhcHN0b25lIiwiaWF0IjoxNTg4Mzc2NDI5LCJleHAiOjE1ODg0NjI3OTYsImF6cCI6IlBaMDA5WkcyRVc4bjVkaXBPR3JkdXExbEVBbzNQRkpiIiwic2NvcGUiOiIiLCJwZXJtaXNzaW9ucyI6WyJkZWxldGU6YWN0b3JzIiwiZ2V0OmFjdG9ycyIsImdldDptb3ZpZXMiLCJwYXRjaDphY3RvcnMiLCJwYXRjaDptb3ZpZXMiLCJwb3N0OmFjdG9ycyJdfQ.eCtSY4h1pYdYeWZbfEIwgv4p7g8j2Vqe-TZGNYXG7I4xvwLnGTQCK1aXIb6B65yKxhtwb-xMfZPWkg6B1HgHwMYtQfObwZEkq1KU5bB76uHLyTZ8scVRU4zy1Dxp8x3IsPtzziD1jDwU6DvGM9Ny2HWikIeJBx9QlcAA0xKp8vrMjztHZBFS0Hi6jQr_S2fD6YTI0Zdn2La_tWThrMstiVvCXk4quO4J5lbqcxjpHSA3y7V6xE4pADNBZYoWAUm5_dxR65MDa9Ld_OAhU6v5CODwuKn4e3xmpygSPUdESwrXJmcj4pdhm1WLrmmGYJG2Jliy9oFFGU5mRXQy_MADDQ",
						"type": "string"
					}
				]
			},
			"event": [
				{
					"listen": "prerequest",
					"script": {
						"id": "b037db8b-a3fc-4b84-8261-ab6e395ea394",
						"type": "text/javascript",
						"exec": [
							""
						]
					}
				},
				{
					"listen": "test",
					"script": {
						"id": "b46bed0e-d2a2-49fa-9588-94d0fc9a3fba",
						"type": "text/javascript",
						"exec": [
							""
						]
					}
				}
			],
			"protocolProfileBehavior": {}
		},
		{
			"name": "Executive Producer",
			"item": [
				{
					"name": "/actors",
					"request": {
						"method": "POST",
						"header": [],
						"body": {
							"mode": "raw",
							"raw": "{\n\t\"id\": 100000\n}\n",
							"options": {
								"raw": {
									"language": "json"
								}
							}
						},
						"url": {
							"raw": "{{host}}/actors",
							"host": [
								"{{host}}"
							],
							"path": [
								"actors"
							]
						}
					},
					"response": []
				},
				{
					"name": "/movies",
					"request": {
						"method": "POST",
						"header": [],
						"body": {
							"mode": "raw",
							"raw": "{\n    \"title\": \"The Other Guys\",\n    \"release_date\": \"08-06-2010\"\n}\n",
							"options": {
								"raw": {
									"language": "json"
								}
							}
						},
						"url": {
							"raw": "{{host}}/movies",
							"host": [
								"{{host}}"
							],
							"path": [
								"movies"
							]
						}
					},
					"response": []
				},
				{
					"name": "/actors",
					"request": {
						"method": "GET",
						"header": [],
						"url": {
							"raw": "{{host}}/actors",
							"host": [
								"{{host}}"
							],
							"path": [
								"actors"
							]
						}
					},
					"response": []
				},
				{
					"name": "/movies",
					"request": {
						"method": "GET",
						"header": [],
						"url": {
							"raw": "{{host}}/movies",
							"host": [
								"{{host}}"
							],
							"path": [
								"movies"
							]
						}
					},
					"response": []
				},
				{
					"name": "/movies",
					"request": {
						"method": "PATCH",
						"header": [],
						"body": {
							"mode": "raw",
							"raw": "{\n    \"release_date\": \"08-06-2012\"\n}\n",
							"options": {
								"raw": {
									"language": "json"
								}
							}
						},
						"url": {
							"raw": "{{host}}/movies/4",
							"host": [
								"{{host}}"
							],
							"path": [
								"movies",
								"4"
							]
						}
					},
					"response": []
				},
				{
					"name": "/actors",
					"request": {
						"method": "PATCH",
						"header": [],
						"body": {
							"mode": "raw",
							"raw": "{\n    \"gender\": \"Female\"\n}\n",
							"options": {
								"raw": {
									"language": "json"
								}
							}
						},
						"url": {
							"raw": "{{host}}/actors/5",
							"host": [
								"{{host}}"
							],
							"path": [
								"actors",
								"5"
							]
						}
					},
					"response": []
				},
				{
					"name": "/movies",
					"request": {
						"method": "DELETE",
						"header": [],
						"url": {
							"raw": "{{host}}/movies/1",
							"host": [
								"{{host}}"
							],
							"path": [
								"movies",
								"1"
							]
						}
					},
					"response": []
				},
				{
					"name": "/actors",
					"request": {
						"method": "DELETE",
						"header": [],
						"url": {
							"raw": "{{host}}/actors/2",
							"host": [
								"{{host}}"
							],
							"path": [
								"actors",
								"2"
							]
						}
					},
					"response": []
				}
			],
			"auth": {
				"type": "bearer",
				"bearer": [
					{
						"key": "token",
						"value": "eyJhbGciOiJSUzI1NiIsInR5cCI6IkpXVCIsImtpZCI6Ik5FRTBRakpEUXpjM05qSTRNVEV5UlRRelEwVTRNa0ZDUmpKRVFUQTFSVVkwTnpJek1VSkdRdyJ9.eyJpc3MiOiJodHRwczovL2pvbnNoZWZmZXIuYXV0aDAuY29tLyIsInN1YiI6ImF1dGgwfDVlNWVkNGQyODhlYzE3MGQ2YjhmMjZiNCIsImF1ZCI6ImNhcHN0b25lIiwiaWF0IjoxNTg4Mzc2Mzc2LCJleHAiOjE1ODg0NjI3NDMsImF6cCI6IlBaMDA5WkcyRVc4bjVkaXBPR3JkdXExbEVBbzNQRkpiIiwic2NvcGUiOiIiLCJwZXJtaXNzaW9ucyI6WyJkZWxldGU6YWN0b3JzIiwiZGVsZXRlOm1vdmllcyIsImdldDphY3RvcnMiLCJnZXQ6bW92aWVzIiwicGF0Y2g6YWN0b3JzIiwicGF0Y2g6bW92aWVzIiwicG9zdDphY3RvcnMiLCJwb3N0Om1vdmllcyJdfQ.f57QoOG7LulhyPnqEvTfC9vR7sGghIlhbYYj0yzB7egdRMnpxXXvgVyk33kVAzUNyLDpbdURV0g9vEQqvDfBRUwVcEoyLMlH5Bn7Jg9Yo7HeW6s_mjRbyQjWKkt8qeEhhvlVx5WkGihMBPgy3ij0Z-aAkIdlrzE5e2_HGoQxPpXNh5mzkQ9sUMcnLZKe95UBHhc7CvU-tUTTovL4qXyPOsdiNxAsIWEuyr9yfa3jWGF2OF5KVk70epnglhfFULgL-amGFoyaiKRtSH7hlF93NB1a6wydasCBsGzxtCVHlFzYSZDJvgh7xNPDx6sYelZSdTJ3Pq-CWqzOP0viQ3toHw",
						"type": "string"
					}
				]
			},
			"event": [
				{
					"listen": "prerequest",
					"script": {
						"id": "8bd007c6-3479-4ef6-b128-9c449e539805",
						"type": "text/javascript",
						"exec": [
							""
						]
					}
				},
				{
					"listen": "test",
					"script": {
						"id": "15602ecd-c4ed-43cf-95f2-c44c1d5c294c",
						"type": "text/javascript",
						"exec": [
							""
						]
					}
				}
			],
			"protocolProfileBehavior": {}
		}
	],
	"event": [
		{
			"listen": "prerequest",
			"script": {
				"id": "41b937e9-6937-499d-aab9-d0739fa4bfd3",
				"type": "text/javascript",
				"exec": [
					""
				]
			}
		},
		{
			"listen": "test",
			"script": {
				"id": "5b73cddc-98b7-4272-8a1c-015d321672c4",
				"type": "text/javascript",
				"exec": [
					""
				]
			}
		}
	],
	"variable": [
		{
			"id": "f987653d-8a1a-442c-985a-92d03458c816",
			"key": "host",
			"value": "http://127.0.0.1:5000/",
			"type": "string"
		}
	],
	"protocolProfileBehavior": {}
}